{"factura":{"IDE":{"numeracion":"F100-00000038","fechaEmision":"2023-01-14","horaEmision":"16:32:00","codTipoDocumento":"01","tipoMoneda":"PEN","numeroOrdenCompra":"","fechaVencimiento":""},"EMI":{"tipoDocId":"6","numeroDocId":"20295754444","nombreComercial":"","razonSocial":"IBERO A. & G. S.A.C.","direccion":"Av. Oscar R. Benavides Nro. 500 (Ex Av. Diagonal - Esq. con Calle Berlin) ","departamento":"Lima","provincia":"","distrito":"","codigoPais":"PE","telefono":"015006720","correoElectronico":"fe@ibero.com.pe","codigoAsigSUNAT":"0000"},"REC":{"tipoDocId":"6","numeroDocId":"10757601783","razonSocial":"SOTELO ROJAS JHOE ALEXANDERS","direccion":" ","departamento":"","provincia":"","distrito":"","codigoPais":"PE","telefono":"","correoElectronico":""},"DRF":[],"CAB":{"exoneradas":{"codigo":"1003","totalVentas":"248.00"},"totalImpuestos":[{"idImpuesto":"9997","montoImpuesto":"0.00"}],"importeTotal":"248.00","tipoOperacion":"0101","leyenda":[{"codigo":"1000","descripcion":"DOSCIENTOS CUARENTA Y OCHO SOLES "}],"montoTotalImpuestos":"0.00"},"DET":[{"numeroItem":"1","codigoProducto":"9788439739500","descripcionProducto":"EL HOMBRE REBELDE","cantidadItems":"1","unidad":"NIU","valorUnitario":"129","precioVentaUnitario":"129","totalImpuestos":[{"idImpuesto":"9997","montoImpuesto":"0.00","tipoAfectacion":"20","montoBase":"129","porcentaje":"0"}],"valorVenta":"129","montoTotalImpuestos":"0"},{"numeroItem":"2","codigoProducto":"9788418056703","descripcionProducto":"VIVIR LA LUCIDEZ. TODOS LOS CARNETS (1935 - 1959)","cantidadItems":"1","unidad":"NIU","valorUnitario":"119","precioVentaUnitario":"119","totalImpuestos":[{"idImpuesto":"9997","montoImpuesto":"0.00","tipoAfectacion":"20","montoBase":"119","porcentaje":"0"}],"valorVenta":"119","montoTotalImpuestos":"0"}],"ADI":[{"tituloAdicional":"CUENTAS CORRIENTES","valorAdicional":""}]}}