{"factura":{"IDE":{"numeracion":"F104-00000012","fechaEmision":"2023-01-10","horaEmision":"13:46:00","codTipoDocumento":"01","tipoMoneda":"PEN","numeroOrdenCompra":"","fechaVencimiento":""},"EMI":{"tipoDocId":"6","numeroDocId":"20295754444","nombreComercial":"","razonSocial":"IBERO A. & G. S.A.C.","direccion":"Av. Oscar R. Benavides Nro. 500 (Ex Av. Diagonal - Esq. con Calle Berlin) ","departamento":"Lima","provincia":"","distrito":"","codigoPais":"PE","telefono":"+51 987 113 775","correoElectronico":"fe@ibero.com.pe","codigoAsigSUNAT":"0000"},"REC":{"tipoDocId":"6","numeroDocId":"20602959598","razonSocial":"LIPOSUCCION DE ALTA DEFINICION S.A.C.","direccion":"AV. CIRCUNVALACION CLUB GOLF 206 INT. 902A - URB. CLUB GOLF LOS INCAS SAN ISIDRO","departamento":"LIMA","provincia":"LIMA","distrito":"","codigoPais":"PE","telefono":"","correoElectronico":""},"DRF":[],"CAB":{"gravadas":{"codigo":"1001","totalVentas":"400.35"},"totalImpuestos":[{"idImpuesto":"1000","montoImpuesto":"72.06"}],"importeTotal":"472.41","tipoOperacion":"0101","leyenda":[{"codigo":"1000","descripcion":"CUATROCIENTOS SETENTA Y DOS SOLES CON CUARENTA Y UN CENTIMOS"}],"montoTotalImpuestos":"72.06"},"DET":[{"numeroItem":"1","codigoProducto":"7755429000010","descripcionProducto":"LIBRETA VANTAGE CLASSICA 14X21","cantidadItems":"15","unidad":"NIU","valorUnitario":"26.69","precioVentaUnitario":"31.4942","totalImpuestos":[{"idImpuesto":"1000","montoImpuesto":"72.06","tipoAfectacion":"10","montoBase":"400.35","porcentaje":"18"}],"valorVenta":"400.35","montoTotalImpuestos":"72.06"}],"ADI":[{"tituloAdicional":"CUENTAS CORRIENTES","valorAdicional":""}]}}