{"factura":{"IDE":{"numeracion":"F105-00000035","fechaEmision":"2023-01-17","horaEmision":"14:07:00","codTipoDocumento":"01","tipoMoneda":"PEN","numeroOrdenCompra":"","fechaVencimiento":""},"EMI":{"tipoDocId":"6","numeroDocId":"20295754444","nombreComercial":"","razonSocial":"IBERO A. & G. S.A.C.","direccion":"Av. Oscar R. Benavides Nro. 500 (Ex Av. Diagonal - Esq. con Calle Berlin) ","departamento":"Lima","provincia":"","distrito":"","codigoPais":"PE","telefono":"015006720","correoElectronico":"fe@ibero.com.pe","codigoAsigSUNAT":"0000"},"REC":{"tipoDocId":"6","numeroDocId":"20452357420","razonSocial":"ANDINAS SERVICE TOURS E.I.R.L.","direccion":"103 INT. D - URB. SANTA MARIA DE SARAJA ICA","departamento":"ICA","provincia":"ICA","distrito":"","codigoPais":"PE","telefono":"","correoElectronico":""},"DRF":[],"CAB":{"exoneradas":{"codigo":"1003","totalVentas":"79.90"},"totalImpuestos":[{"idImpuesto":"9997","montoImpuesto":"0.00"}],"importeTotal":"79.90","tipoOperacion":"0101","leyenda":[{"codigo":"1000","descripcion":"SETENTA Y NUEVE SOLES CON NOVENTA CENTIMOS"}],"montoTotalImpuestos":"0.00"},"DET":[{"numeroItem":"1","codigoProducto":"9786124461187","descripcionProducto":"COMPAS 8. LOS COMPAS Y LA AVENTURA EN MINIATURA","cantidadItems":"1","unidad":"NIU","valorUnitario":"79.9","precioVentaUnitario":"79.9","totalImpuestos":[{"idImpuesto":"9997","montoImpuesto":"0.00","tipoAfectacion":"20","montoBase":"79.9","porcentaje":"0"}],"valorVenta":"79.9","montoTotalImpuestos":"0"}],"ADI":[{"tituloAdicional":"CUENTAS CORRIENTES","valorAdicional":""}]}}